{
  "date": "2026-04-12",
  "fetched_at": "2026-04-12T02:03:16.995249-04:00",
  "source": "rotowire",
  "source_label": "Rotowire NBA",
  "url": "https://www.rotowire.com/rss/news.php?sport=NBA",
  "type": "rss",
  "raw_text": "<?xml version=\"1.0\" encoding=\"UTF-8\"?>\n<rss version=\"2.0\">\n  <channel>\n    <title>RotoWire.com Latest NBA News</title>\n    <copyright>Copyright (c) 2026 Roto Sports, Inc, All rights reserved.</copyright>\n    <description>Fantasy Sports from RotoWire.com</description>\n    <category>Fantasy Sports</category>\n    <language>en-us</language>\n    <ttl>10</ttl>\n    <image>\n      <title>RotoWire.com Fantasy Sports</title>\n      <width>120</width>\n      <height>30</height>\n      <link>https://www.rotowire.com</link>\n      <url>https://content.rotowire.com/images/logo_roto_small.gif</url>\n    </image>\n    <link>https://www.rotowire.com</link>\n    <item>\n        <guid>nba529029</guid>\n        <title>Cedric Coward: Won't play Sunday</title>\n        <link>https://www.rotowire.com//basketball/player/cedric-coward-6592</link>\n        <description>Coward (back) has been ruled out for Sunday's game against Houston.\n\n        Visit RotoWire.com for more analysis on this update.</description>\n        <pubDate>Sat, 11 Apr 2026 7:11:00 PM PDT</pubDate>\n    </item>\n    <item>\n        <guid>nba529023</guid>\n        <title>Mark Williams: Questionable for Sunday</title>\n        <link>https://www.rotowire.com//basketball/player/mark-williams-5647</link>\n        <description>Williams (foot) is listed as questionable for Sunday's game against the Thunder.\n\n        Visit RotoWire.com for more analysis on this update.</description>\n        <pubDate>Sat, 11 Apr 2026 6:55:00 PM PDT</pubDate>\n    </item>\n    <item>\n        <guid>nba529021</guid>\n        <title>Collin Gillespie: Iffy to face OKC</title>\n        <link>https://www.rotowire.com//basketball/player/collin-gillespie-5732</link>\n        <description>Gillespie is listed as questionable for Sunday's game against the Thunder due to a right shoulder contusion.\n\n        Visit RotoWire.com for more analysis on this update.</description>\n        <pubDate>Sat, 11 Apr 2026 6:52:00 PM PDT</pubDate>\n    </item>\n    <item>\n        <guid>nba529016</guid>\n        <title>Jalen Green: Iffy for Sunday</title>\n        <link>https://www.rotowire.com//basketball/player/jalen-green-5230</link>\n        <description>Green is listed as questionable for Sunday's game against the Thunder due to right knee soreness.\n\n        Visit RotoWire.com for more analysis on this update.</description>\n        <pubDate>Sat, 11 Apr 2026 6:48:00 PM PDT</pubDate>\n    </item>\n    <item>\n        <guid>nba529015</guid>\n        <title>Anthony Edwards: Sitting out Sunday's game</title>\n        <link>https://www.rotowire.com//basketball/player/anthony-edwards-5110</link>\n        <description>Edwards won't play Sunday against the Pelicans due to right knee injury maintenance.\n\n        Visit RotoWire.com for more analysis on this update.</description>\n        <pubDate>Sat, 11 Apr 2026 6:41:00 PM PDT</pubDate>\n    </item>\n  </channel>\n</rss>\n",
  "fetch_error": null
}