{"id": "cb55f248d8dbb539ca55edf31d762f6a", "sport_key": "basketball_nba", "sport_title": "NBA", "commence_time": "2026-04-03T23:40:00Z", "home_team": "Brooklyn Nets", "away_team": "Atlanta Hawks", "bookmakers": [{"key": "fanduel", "title": "FanDuel", "markets": [{"key": "h2h", "last_update": "2026-04-03T16:04:09Z", "outcomes": [{"name": "Atlanta Hawks", "price": 1.05}, {"name": "Brooklyn Nets", "price": 12.0}]}, {"key": "spreads", "last_update": "2026-04-03T16:04:09Z", "outcomes": [{"name": "Atlanta Hawks", "price": 1.95, "point": -17.5}, {"name": "Brooklyn Nets", "price": 1.87, "point": 17.5}]}, {"key": "totals", "last_update": "2026-04-03T16:04:09Z", "outcomes": [{"name": "Over", "price": 1.91, "point": 225.5}, {"name": "Under", "price": 1.91, "point": 225.5}]}]}, {"key": "fanatics", "title": "Fanatics", "markets": [{"key": "h2h", "last_update": "2026-04-03T16:03:51Z", "outcomes": [{"name": "Atlanta Hawks", "price": 1.06}, {"name": "Brooklyn Nets", "price": 10.0}]}, {"key": "spreads", "last_update": "2026-04-03T16:03:51Z", "outcomes": [{"name": "Atlanta Hawks", "price": 1.91, "point": -17.0}, {"name": "Brooklyn Nets", "price": 1.91, "point": 17.0}]}, {"key": "totals", "last_update": "2026-04-03T16:03:51Z", "outcomes": [{"name": "Over", "price": 1.91, "point": 225.5}, {"name": "Under", "price": 1.91, "point": 225.5}]}]}, {"key": "draftkings", "title": "DraftKings", "markets": [{"key": "h2h", "last_update": "2026-04-03T16:03:11Z", "outcomes": [{"name": "Atlanta Hawks", "price": 1.06}, {"name": "Brooklyn Nets", "price": 10.5}]}, {"key": "spreads", "last_update": "2026-04-03T16:03:11Z", "outcomes": [{"name": "Atlanta Hawks", "price": 1.95, "point": -17.5}, {"name": "Brooklyn Nets", "price": 1.87, "point": 17.5}]}, {"key": "totals", "last_update": "2026-04-03T16:03:11Z", "outcomes": [{"name": "Over", "price": 1.91, "point": 225.5}, {"name": "Under", "price": 1.91, "point": 225.5}]}]}, {"key": "mybookieag", "title": "MyBookie.ag", "markets": [{"key": "h2h", "last_update": "2026-04-03T16:02:58Z", "outcomes": [{"name": "Atlanta Hawks", "price": 1.05}, {"name": "Brooklyn Nets", "price": 9.84}]}, {"key": "spreads", "last_update": "2026-04-03T16:02:58Z", "outcomes": [{"name": "Atlanta Hawks", "price": 1.91, "point": -17.0}, {"name": "Brooklyn Nets", "price": 1.91, "point": 17.0}]}, {"key": "totals", "last_update": "2026-04-03T16:02:58Z", "outcomes": [{"name": "Over", "price": 1.91, "point": 226.0}, {"name": "Under", "price": 1.91, "point": 226.0}]}]}, {"key": "williamhill_us", "title": "Caesars", "markets": [{"key": "h2h", "last_update": "2026-04-03T16:01:29Z", "outcomes": [{"name": "Atlanta Hawks", "price": 1.06}, {"name": "Brooklyn Nets", "price": 10.5}]}, {"key": "spreads", "last_update": "2026-04-03T16:01:29Z", "outcomes": [{"name": "Atlanta Hawks", "price": 1.87, "point": -17.0}, {"name": "Brooklyn Nets", "price": 1.95, "point": 17.0}]}, {"key": "totals", "last_update": "2026-04-03T16:01:29Z", "outcomes": [{"name": "Over", "price": 1.91, "point": 225.5}, {"name": "Under", "price": 1.91, "point": 225.5}]}]}, {"key": "lowvig", "title": "LowVig.ag", "markets": [{"key": "h2h", "last_update": "2026-04-03T16:03:57Z", "outcomes": [{"name": "Atlanta Hawks", "price": 1.06}, {"name": "Brooklyn Nets", "price": 10.89}]}, {"key": "spreads", "last_update": "2026-04-03T16:03:57Z", "outcomes": [{"name": "Atlanta Hawks", "price": 1.94, "point": -17.0}, {"name": "Brooklyn Nets", "price": 1.94, "point": 17.0}]}, {"key": "totals", "last_update": "2026-04-03T16:03:57Z", "outcomes": [{"name": "Over", "price": 1.98, "point": 226.0}, {"name": "Under", "price": 1.88, "point": 226.0}]}]}, {"key": "betonlineag", "title": "BetOnline.ag", "markets": [{"key": "h2h", "last_update": "2026-04-03T16:03:37Z", "outcomes": [{"name": "Atlanta Hawks", "price": 1.06}, {"name": "Brooklyn Nets", "price": 10.45}]}, {"key": "spreads", "last_update": "2026-04-03T16:03:37Z", "outcomes": [{"name": "Atlanta Hawks", "price": 1.91, "point": -17.0}, {"name": "Brooklyn Nets", "price": 1.91, "point": 17.0}]}, {"key": "totals", "last_update": "2026-04-03T16:03:37Z", "outcomes": [{"name": "Over", "price": 1.95, "point": 226.0}, {"name": "Under", "price": 1.87, "point": 226.0}]}]}, {"key": "betmgm", "title": "BetMGM", "markets": [{"key": "h2h", "last_update": "2026-04-03T16:03:37Z", "outcomes": [{"name": "Atlanta Hawks", "price": 1.05}, {"name": "Brooklyn Nets", "price": 10.5}]}, {"key": "spreads", "last_update": "2026-04-03T16:03:37Z", "outcomes": [{"name": "Atlanta Hawks", "price": 1.95, "point": -17.5}, {"name": "Brooklyn Nets", "price": 1.87, "point": 17.5}]}, {"key": "totals", "last_update": "2026-04-03T16:03:37Z", "outcomes": [{"name": "Over", "price": 1.91, "point": 225.5}, {"name": "Under", "price": 1.91, "point": 225.5}]}]}, {"key": "betrivers", "title": "BetRivers", "markets": [{"key": "h2h", "last_update": "2026-04-03T16:03:50Z", "outcomes": [{"name": "Atlanta Hawks", "price": 1.06}, {"name": "Brooklyn Nets", "price": 9.0}]}, {"key": "spreads", "last_update": "2026-04-03T16:03:50Z", "outcomes": [{"name": "Atlanta Hawks", "price": 1.88, "point": -16.5}, {"name": "Brooklyn Nets", "price": 1.92, "point": 16.5}]}, {"key": "totals", "last_update": "2026-04-03T16:03:50Z", "outcomes": [{"name": "Over", "price": 1.88, "point": 225.5}, {"name": "Under", "price": 1.91, "point": 225.5}]}]}, {"key": "betus", "title": "BetUS", "markets": [{"key": "h2h", "last_update": "2026-04-03T16:04:22Z", "outcomes": [{"name": "Atlanta Hawks", "price": 1.06}, {"name": "Brooklyn Nets", "price": 10.5}]}, {"key": "spreads", "last_update": "2026-04-03T16:04:22Z", "outcomes": [{"name": "Atlanta Hawks", "price": 1.91, "point": -17.0}, {"name": "Brooklyn Nets", "price": 1.91, "point": 17.0}]}, {"key": "totals", "last_update": "2026-04-03T16:04:22Z", "outcomes": [{"name": "Over", "price": 1.91, "point": 225.5}, {"name": "Under", "price": 1.91, "point": 225.5}]}]}, {"key": "bovada", "title": "Bovada", "markets": [{"key": "h2h", "last_update": "2026-04-03T16:04:38Z", "outcomes": [{"name": "Atlanta Hawks", "price": 1.06}, {"name": "Brooklyn Nets", "price": 9.0}]}, {"key": "spreads", "last_update": "2026-04-03T16:04:38Z", "outcomes": [{"name": "Atlanta Hawks", "price": 1.95, "point": -17.0}, {"name": "Brooklyn Nets", "price": 1.87, "point": 17.0}]}, {"key": "totals", "last_update": "2026-04-03T16:04:38Z", "outcomes": [{"name": "Over", "price": 1.91, "point": 225.5}, {"name": "Under", "price": 1.91, "point": 225.5}]}]}]}